tree_sitter_glsl37/__init__.py
tree_sitter_glsl37/__init__.pyi
tree_sitter_glsl37/_binding.pyd
tree_sitter_glsl37/py.typed
tree_sitter_glsl37-0.2.0.dist-info/LICENSE
tree_sitter_glsl37-0.2.0.dist-info/METADATA
tree_sitter_glsl37-0.2.0.dist-info/WHEEL
tree_sitter_glsl37-0.2.0.dist-info/top_level.txt
tree_sitter_glsl37-0.2.0.dist-info/RECORD
