Metadata-Version: 2.1
Name: tree-sitter-glsl37
Version: 0.2.0
Summary: Glsl grammar for tree-sitter
License: MIT
Project-URL: Homepage, https://github.com/tree-sitter-grammars/tree-sitter-glsl
Keywords: incremental,parsing,tree-sitter,glsl
Classifier: Intended Audience :: Developers
Classifier: License :: OSI Approved :: MIT License
Classifier: Topic :: Software Development :: Compilers
Classifier: Topic :: Text Processing :: Linguistic
Classifier: Typing :: Typed
Requires-Python: >=3.7
License-File: LICENSE
Provides-Extra: core
Requires-Dist: tree-sitter~=0.21; extra == "core"
